{
	"InputWeapons": {
		"WeaponEditorIDs": [
			"OrcishClaws",
			"OrcishClawsLeft",
			"OrcishHalberd",
			"OrcishPike",
			"OrcishQStaff",
			"OrcishRapier",
			"OrcishWhip",
			
			"DwarvenClaws",
			"DwarvenClawsLeft",
			"DwarvenHalberd",
			"DwarvenPike",
			"DwarvenQStaff",
			"DwarvenRapier",
			"DwarvenWhip",
			
			"ElvenClaws",
			"ElvenClawsLeft",
			"ElvenHalberd",
			"ElvenPike",
			"ElvenQStaff",
			"ElvenRapier",
			"ElvenWhip",
			
			"GlassClaws",
			"GlassClawsLeft",
			"GlassHalberd",
			"GlassPike",
			"GlassQStaff",
			"GlassRapier",
			"GlassWhip",
			
			"EbonyClaws",
			"EbonyClawsLeft",
			"EbonyHalberd",
			"EbonyPike",
			"EbonyQStaff",
			"EbonyRapier",
			"EbonyWhip",
			
			"DaedricClaws",
			"DaedricClawsLeft",
			"DaedricHalberd",
			"DaedricPike",
			"DaedricQStaff",
			"DaedricRapier",
			"DaedricWhip"
		],
		
		"LeveledListPrefix": "SublistEnchWeapon_",
		"LeveledListSuffix": "_04",
		
		"Enchantments": [
			{
				"EditorID": "EnchWeaponFrostDamage04",
				"Suffix": " of Freezing",
				"EnchantmentAmount": 2000
			},
			{
				"EditorID": "EnchWeaponFireDamage04",
				"Suffix": " of Fire",
				"EnchantmentAmount": 2000
			},
			{
				"EditorID": "EnchWeaponShockDamage04",
				"Suffix": " of Thunderbolts",
				"EnchantmentAmount": 2000
			},
			{
				"EditorID": "EnchWeaponStaminaDamage04",
				"Suffix": " of Debilitation",
				"EnchantmentAmount": 2000
			},
			{
				"EditorID": "EnchWeaponMagickaDamage04",
				"Suffix": " of Depleting",
				"EnchantmentAmount": 2000
			},
			{
				"EditorID": "EnchWeaponAbsorbHealth04",
				"Suffix": " of Devouring",
				"EnchantmentAmount": 2000
			},
			{
				"EditorID": "EnchWeaponAbsorbMagicka04",
				"Suffix": " of Winnowing",
				"EnchantmentAmount": 2000
			},
			{
				"EditorID": "EnchWeaponAbsorbStamina04",
				"Suffix": " of Harvesting",
				"EnchantmentAmount": 2000
			},
			{
				"EditorID": "EnchWeaponSoulTrap04",
				"Suffix": " of Animus",
				"EnchantmentAmount": 2000
			},
			{
				"EditorID": "EnchWeaponFear04",
				"Suffix": " of Despair",
				"EnchantmentAmount": 2000
			},
			{
				"EditorID": "EnchWeaponTurnUndead04",
				"Prefix": "Hallowed ",
				"EnchantmentAmount": 2000
			}
		]
	}
}

